AnzhuoxiaoZhaoMianshiZhinan/README.md
AnzhuoxiaoZhaoMianshiZhinan/__init__.py
AnzhuoxiaoZhaoMianshiZhinan/__main__.py
AnzhuoxiaoZhaoMianshiZhinan/file.epub
AnzhuoxiaoZhaoMianshiZhinan/index.html
AnzhuoxiaoZhaoMianshiZhinan/css/__init__.py
AnzhuoxiaoZhaoMianshiZhinan/css/annotations.css
AnzhuoxiaoZhaoMianshiZhinan/css/main.css
AnzhuoxiaoZhaoMianshiZhinan/css/normalize.css
AnzhuoxiaoZhaoMianshiZhinan/css/popup.css
AnzhuoxiaoZhaoMianshiZhinan/font/__init__.py
AnzhuoxiaoZhaoMianshiZhinan/font/fontello.eot
AnzhuoxiaoZhaoMianshiZhinan/font/fontello.svg
AnzhuoxiaoZhaoMianshiZhinan/font/fontello.ttf
AnzhuoxiaoZhaoMianshiZhinan/font/fontello.woff
AnzhuoxiaoZhaoMianshiZhinan/img/__init__.py
AnzhuoxiaoZhaoMianshiZhinan/img/annotator-glyph-sprite.png
AnzhuoxiaoZhaoMianshiZhinan/img/annotator-icon-sprite.png
AnzhuoxiaoZhaoMianshiZhinan/img/apple-touch-icon.png
AnzhuoxiaoZhaoMianshiZhinan/img/cancelfullscreen.png
AnzhuoxiaoZhaoMianshiZhinan/img/close.png
AnzhuoxiaoZhaoMianshiZhinan/img/fullscreen.png
AnzhuoxiaoZhaoMianshiZhinan/img/loader.gif
AnzhuoxiaoZhaoMianshiZhinan/img/menu-icon.png
AnzhuoxiaoZhaoMianshiZhinan/img/save.png
AnzhuoxiaoZhaoMianshiZhinan/img/saved.png
AnzhuoxiaoZhaoMianshiZhinan/img/settings-s.png
AnzhuoxiaoZhaoMianshiZhinan/img/settings.png
AnzhuoxiaoZhaoMianshiZhinan/img/star.png
AnzhuoxiaoZhaoMianshiZhinan/js/__init__.py
AnzhuoxiaoZhaoMianshiZhinan/js/epub.js
AnzhuoxiaoZhaoMianshiZhinan/js/epub.min.js
AnzhuoxiaoZhaoMianshiZhinan/js/epub.min.map
AnzhuoxiaoZhaoMianshiZhinan/js/hooks.min.js
AnzhuoxiaoZhaoMianshiZhinan/js/hooks.min.map
AnzhuoxiaoZhaoMianshiZhinan/js/reader.js
AnzhuoxiaoZhaoMianshiZhinan/js/reader.js.map
AnzhuoxiaoZhaoMianshiZhinan/js/reader.min.js
AnzhuoxiaoZhaoMianshiZhinan/js/reader.min.map
AnzhuoxiaoZhaoMianshiZhinan/js/hooks/__init__.py
AnzhuoxiaoZhaoMianshiZhinan/js/hooks/extensions/__init__.py
AnzhuoxiaoZhaoMianshiZhinan/js/hooks/extensions/highlight.js
AnzhuoxiaoZhaoMianshiZhinan/js/libs/__init__.py
anzhuoxiao_zhao_mianshi_zhinan-2024.3.3.0.dist-info/METADATA
anzhuoxiao_zhao_mianshi_zhinan-2024.3.3.0.dist-info/WHEEL
anzhuoxiao_zhao_mianshi_zhinan-2024.3.3.0.dist-info/entry_points.txt
anzhuoxiao_zhao_mianshi_zhinan-2024.3.3.0.dist-info/top_level.txt
anzhuoxiao_zhao_mianshi_zhinan-2024.3.3.0.dist-info/RECORD
